<?xml version="1.0"?>
<!DOCTYPE hibernate-mapping PUBLIC "-//Hibernate/Hibernate Mapping DTD 3.0//EN"
"http://hibernate.sourceforge.net/hibernate-mapping-3.0.dtd">
	<!-- 
    Mapping file autogenerated by MyEclipse - Hibernate Tools
	-->
<hibernate-mapping package="de.act.central.types" auto-import="true" default-lazy="false">
	<class name="AccountingInformation" table="f_aci" schema="public">
		<cache usage="transactional" />
		<composite-id>
			<key-many-to-one name="FAtt" class="Attachment">
				<column name="att_id" not-null="true" unique="true" />
			</key-many-to-one>
			<key-property name="aciSeq" column="aci_seq" type="java.lang.Short"/>
		</composite-id>
		<many-to-one name="FAtt" class="Attachment" update="false" insert="false">
			<column name="att_id" not-null="true" />
		</many-to-one>
		<property name="aciId" type="java.lang.String">
			<column name="aci_id" length="8" />
		</property>
		<property name="aciRem" type="java.lang.String">
			<column name="aci_rem" length="100" />
		</property>
		<property name="corr" type="java.util.Date" insert="false" update="false">
			<column name="corr" length="8" />
		</property>
	</class>
</hibernate-mapping>
